cosmoTransitions/__init__.py
cosmoTransitions/finiteT.py
cosmoTransitions/generic_potential.py
cosmoTransitions/helper_functions.py
cosmoTransitions/multi_field_plotting.py
cosmoTransitions/pathDeformation.py
cosmoTransitions/transitionFinder.py
cosmoTransitions/tunneling1D.py
cosmoTransitions/examples/__init__.py
cosmoTransitions/examples/fullTunneling.py
cosmoTransitions/examples/testModel1.py
cosmoTransitions-2.0.7.dist-info/LICENSE.txt
cosmoTransitions-2.0.7.dist-info/METADATA
cosmoTransitions-2.0.7.dist-info/WHEEL
cosmoTransitions-2.0.7.dist-info/top_level.txt
cosmoTransitions-2.0.7.dist-info/RECORD
