Metadata-Version: 2.1
Name: cosmoTransitions
Version: 2.0.7
Summary: A package for analyzing finite or zero-temperature cosmological phase transitions driven by single or multiple scalar fields.
Home-page: https://github.com/clwainwright/CosmoTransitions
Author: Carroll L. Wainwright
Author-email: clwainwri@gmail.com
License: MIT
Classifier: Development Status :: 5 - Production/Stable
Classifier: License :: OSI Approved :: MIT License
Classifier: Programming Language :: Python :: 2
Classifier: Programming Language :: Python :: 2.7
Classifier: Programming Language :: Python :: 3
Classifier: Programming Language :: Python :: 3.4
License-File: LICENSE.txt
Requires-Dist: numpy >=1.8
Requires-Dist: scipy >=0.11
